MANIFEST.in
README.rst
buildout.cfg
develop.cfg
requirements.txt
setup.py
version.txt
bob/__init__.py
bob.db.cuhk_cufs.egg-info/PKG-INFO
bob.db.cuhk_cufs.egg-info/SOURCES.txt
bob.db.cuhk_cufs.egg-info/dependency_links.txt
bob.db.cuhk_cufs.egg-info/entry_points.txt
bob.db.cuhk_cufs.egg-info/namespace_packages.txt
bob.db.cuhk_cufs.egg-info/not-zip-safe
bob.db.cuhk_cufs.egg-info/requires.txt
bob.db.cuhk_cufs.egg-info/top_level.txt
bob/db/__init__.py
bob/db/cuhk_cufs/__init__.py
bob/db/cuhk_cufs/create.py
bob/db/cuhk_cufs/driver.py
bob/db/cuhk_cufs/models.py
bob/db/cuhk_cufs/query.py
bob/db/cuhk_cufs/test.py
bob/db/cuhk_cufs/utils.py
bob/db/cuhk_cufs/scripts/__init__.py
doc/conf.py
doc/guide.rst
doc/index.rst
doc/py_api.rst