Metadata-Version: 1.1
Name: bob.db.cuhk-cufs
Version: 2.2.7
Summary: CUHK Face Sketch Database (CUFS)
Home-page: https://gitlab.idiap.ch/bob/bob.db.cuhk_cufs
Author: Tiago de Freitas Pereira
Author-email: tiago.pereira@idiap.ch
License: BSD
Platform: UNKNOWN
Classifier: Development Status :: 5 - Production/Stable
Classifier: Intended Audience :: Education
Classifier: License :: OSI Approved :: BSD License
Classifier: Natural Language :: English
Classifier: Programming Language :: Python
Classifier: Programming Language :: Python :: 3
Classifier: Topic :: Scientific/Engineering :: Artificial Intelligence
Classifier: Topic :: Database :: Front-Ends
